README.txt
setup.py
boois_return_codes/__init__.py
boois_return_codes/return_codes.py
boois_return_codes.egg-info/PKG-INFO
boois_return_codes.egg-info/SOURCES.txt
boois_return_codes.egg-info/dependency_links.txt
boois_return_codes.egg-info/requires.txt
boois_return_codes.egg-info/top_level.txt
boois_return_codes.egg-info/zip-safe